jomiel_messages/__init__.py
jomiel_messages/protobuf/v1beta1/media_pb2.py
jomiel_messages/protobuf/v1beta1/message_pb2.py
jomiel_messages/protobuf/v1beta1/status_pb2.py
jomiel_messages-0.2.1.1.dist-info/LICENSE
jomiel_messages-0.2.1.1.dist-info/METADATA
jomiel_messages-0.2.1.1.dist-info/NOTICE
jomiel_messages-0.2.1.1.dist-info/WHEEL
jomiel_messages-0.2.1.1.dist-info/top_level.txt
jomiel_messages-0.2.1.1.dist-info/zip-safe
jomiel_messages-0.2.1.1.dist-info/RECORD
