Metadata-Version: 2.1
Name: jomiel_messages
Version: 0.2.1.1
Summary: Python bindings for jomiel protobuf messages
Home-page: https://github.com/guendto/jomiel-messages
Author: Toni Gündoğdu
Author-email: 47444442+guendto@users.noreply.github.com
License: Apache2.0
Platform: any
Classifier: Development Status :: 4 - Beta
Classifier: License :: OSI Approved :: Apache Software License
Classifier: Programming Language :: Python :: 3.6
Classifier: Programming Language :: Python :: 3.7
Classifier: Programming Language :: Python :: 3.8
Classifier: Programming Language :: Python :: 3.9
Requires-Python: >=3.6
License-File: LICENSE
License-File: NOTICE
Requires-Dist: protobuf
